[
    {
        "accuracy": 0.4582,
        "batch": 4096,
        "duration": 790089958795,
        "lr": 0.05743652472438611,
        "metric_acc": 0.4582,
        "momentum": 0.8417395293725185,
        "transform": "bf-v1-RandomHorizontalFlip_RandomPosterize_4",
        "uid": "4322f769e119fb61523c50e5e7377eb4",
        "train_stat": {
            "train_loss": 1.4989056770618145,
            "test_loss": 1.5075754324595134,
            "train_accuracy": 0.46614,
            "gradient_norm": 0.9999993695260228,
            "samples_per_second": 2036.5359475783316,
            "best_accuracy": 0.4582,
            "best_epoch": 32,
            "cpu_count": 24,
            "cpu_type": "x86_64",
            "cpu_usage_percent": 0.4,
            "total_ram_kb": 32627556.0,
            "occupied_ram_kb": 9939016.0,
            "ram_usage_percent": 30.5,
            "gpu_type": "NVIDIA GeForce RTX 4090",
            "gpu_memory_kb": 5195270.5,
            "gpu_total_memory_kb": 24658816.0,
            "occupied_gpu_memory_kb": 17754.5,
            "gpu_memory_usage_percent": 0.07
        },
        "epoch_max": 50
    },
    {
        "accuracy": 0.4402,
        "batch": 4096,
        "duration": 302476116659,
        "lr": 0.05743652472438611,
        "momentum": 0.8417395293725185,
        "transform": "bf-v1-RandomHorizontalFlip_RandomPosterize_4",
        "uid": "bed15f44018c1725532e29e59999805c",
        "epoch_max": 50
    }
]
