{
  "model_name": "rag-30ac00d69bd835bd33ae2f012b68c9ce",
  "device_type": "Micro-Star International Co., Ltd. MS-7E27",
  "os_version": "Linux-6.8.0-111-generic-x86_64-with-glibc2.35",
  "valid": true,
  "emulator": false,
  "iterations": 20,
  "error_message": null,
  "unit": "NVIDIA GeForce RTX 4090",
  "duration": 128066,
  "cpu_duration": 128066,
  "cpu_min_duration": 118129,
  "cpu_max_duration": 144941,
  "cpu_std_dev": 7306.086290373695,
  "gpu_duration": 115536,
  "gpu_min_duration": 109567,
  "gpu_max_duration": 150560,
  "gpu_std_dev": 9106.648266696064,
  "total_ram_kb": 31935912,
  "free_ram_kb": 4125244,
  "available_ram_kb": 21628976,
  "cached_kb": 16968816,
  "in_dim_0": 1,
  "in_dim_1": 64,
  "in_dim_2": 64,
  "in_dim_3": 3,
  "device_analytics": {
    "timestamp": "2026-07-06T19:54:04.748331Z",
    "cpu_info": {
      "cpu_cores": 16,
      "processors": [
        {
          "vendor_id": "x86_64",
          "model": "x86_64"
        }
      ],
      "arm_architecture": null
    },
    "timeline": [
      {
        "phase": "before_eval",
        "ts": "2026-07-06T19:54:04.703103Z",
        "sys": {
          "total_ram_bytes": 32702373888,
          "available_ram_bytes": 22123814912,
          "used_ram_bytes": 10578558976,
          "ram_percent": 32.3,
          "cpu_percent": 6.5,
          "process_rss_bytes": 4133941248
        },
        "gpus": [
          {
            "index": 0,
            "name": "NVIDIA GeForce RTX 4090",
            "driver": "595.71.05",
            "memory_total_mb": 24564,
            "memory_used_mb": 4123,
            "memory_free_mb": 19958,
            "util_percent": 0
          }
        ]
      },
      {
        "phase": "after_eval",
        "ts": "2026-07-06T19:54:04.731952Z",
        "sys": {
          "total_ram_bytes": 32702373888,
          "available_ram_bytes": 22148624384,
          "used_ram_bytes": 10553749504,
          "ram_percent": 32.3,
          "cpu_percent": 19.6,
          "process_rss_bytes": 4133941248
        },
        "gpus": [
          {
            "index": 0,
            "name": "NVIDIA GeForce RTX 4090",
            "driver": "595.71.05",
            "memory_total_mb": 24564,
            "memory_used_mb": 4123,
            "memory_free_mb": 19958,
            "util_percent": 0
          }
        ]
      }
    ],
    "profile": {
      "top_ops": [],
      "profiler_traces": [],
      "peak_cpu_rss_bytes": 4133941248,
      "peak_gpu_mb": 4123.0
    }
  }
}