{
    "total_layers": 7,
    "leaf_layers": 5,
    "max_depth": 2,
    "total_params": 1258,
    "trainable_params": 1258,
    "frozen_params": 0,
    "flops": 7340672,
    "model_size_mb": 0.00479888916015625,
    "buffer_size_mb": 0.00025177001953125,
    "total_memory_mb": 0.0050506591796875,
    "dropout_count": 0,
    "has_attention": 0,
    "has_residual_connections": 0,
    "is_resnet_like": 0,
    "is_vgg_like": 0,
    "is_inception_like": 0,
    "is_densenet_like": 0,
    "is_unet_like": 0,
    "is_transformer_like": 0,
    "is_mobilenet_like": 0,
    "is_efficientnet_like": 0,
    "code_length": 7361,
    "num_classes_defined": 3,
    "num_functions_defined": 15,
    "uses_sequential": 1,
    "uses_modulelist": 0,
    "uses_moduledict": 0,
    "meta": {
        "conv_info": {
            "count": 1,
            "kernel_sizes": [
                3
            ],
            "strides": [
                1
            ],
            "padding_values": [
                1
            ],
            "avg_kernel_size": 3.0,
            "avg_stride": 1.0,
            "total_conv_params": 864
        },
        "linear_info": {
            "count": 1,
            "input_dims": [
                32
            ],
            "output_dims": [
                10
            ],
            "total_linear_params": 330,
            "has_bias": [
                true
            ]
        },
        "dropout_rates": [],
        "layer_types": {
            "Conv2d": 1,
            "BatchNorm2d": 1,
            "ReLU": 1,
            "FocalLoss": 1,
            "Linear": 1,
            "count": {
                "activation": {
                    "ReLU": 1
                },
                "normalization": {
                    "BatchNorm2d": 1
                },
                "pooling": {}
            }
        },
        "param_distribution": {
            "Conv2d": 864,
            "BatchNorm2d": 64,
            "Linear": 330
        }
    },
    "code_minhash": {
        "method": "minhash",
        "available": 1,
        "num_perm": 128,
        "shingle_n": 7,
        "hashvalues": [
            1606403,
            15191945,
            514402,
            4463306,
            460985,
            9438516,
            13102513,
            2717090,
            3316097,
            4029407,
            2729236,
            1600229,
            2263230,
            776024,
            796962,
            2617241,
            3430963,
            5692482,
            1656065,
            4440722,
            749526,
            3477022,
            1925431,
            700753,
            6517636,
            183947,
            492707,
            7343735,
            190578,
            1846157,
            4248836,
            10349843,
            286527,
            636900,
            279703,
            1068622,
            3577277,
            1029681,
            316728,
            250553,
            5647398,
            4249338,
            4533904,
            12040820,
            3524126,
            1688979,
            10931,
            8072084,
            3026038,
            1004974,
            3182871,
            1359177,
            89323,
            11241368,
            643241,
            7219765,
            3623168,
            4880176,
            2687360,
            121479,
            4667681,
            987341,
            2726226,
            6948981,
            862609,
            1519403,
            674862,
            1733835,
            6238842,
            7734590,
            183380,
            1025023,
            4817778,
            2134138,
            3094995,
            7457797,
            4342398,
            253931,
            10778268,
            1091598,
            4835742,
            1121846,
            3990618,
            1159947,
            1237080,
            6408875,
            7422542,
            1613302,
            1121895,
            641093,
            3636238,
            3425446,
            788096,
            916583,
            217067,
            1683276,
            2379289,
            2411178,
            4154781,
            13602107,
            225915,
            297060,
            928885,
            369036,
            2166152,
            344884,
            2433059,
            3429178,
            3239182,
            2296222,
            3559851,
            9965311,
            7310432,
            6138707,
            1765422,
            181427,
            970636,
            2954950,
            6591199,
            1446907,
            8226809,
            1954950,
            921612,
            956024,
            1945015,
            4121980,
            5128125,
            3695313
        ]
    },
    "prm_id": "82afebb329a58d96c0b8b927d1c034fd"
}