{
  "model_name": "ga-686",
  "device_type": "Micro-Star International Co., Ltd. MS-7E27",
  "os_version": "Linux-6.8.0-111-generic-x86_64-with-glibc2.35",
  "valid": true,
  "emulator": false,
  "iterations": 20,
  "error_message": null,
  "unit": "NVIDIA GeForce RTX 4090",
  "duration": 6332760,
  "cpu_duration": 6332760,
  "cpu_min_duration": 6201972,
  "cpu_max_duration": 7079583,
  "cpu_std_dev": 210578.7906783979,
  "gpu_duration": 470817,
  "gpu_min_duration": 449535,
  "gpu_max_duration": 666368,
  "gpu_std_dev": 46763.96809354352,
  "total_ram_kb": 31935912,
  "free_ram_kb": 3095792,
  "available_ram_kb": 21252344,
  "cached_kb": 17606748,
  "in_dim_0": 1,
  "in_dim_1": 128,
  "in_dim_2": 128,
  "in_dim_3": 3,
  "device_analytics": {
    "timestamp": "2026-07-07T01:21:03.955406Z",
    "cpu_info": {
      "cpu_cores": 16,
      "processors": [
        {
          "vendor_id": "x86_64",
          "model": "x86_64"
        }
      ],
      "arm_architecture": null
    },
    "timeline": [
      {
        "phase": "before_eval",
        "ts": "2026-07-07T01:21:03.349729Z",
        "sys": {
          "total_ram_bytes": 32702373888,
          "available_ram_bytes": 21898235904,
          "used_ram_bytes": 10804137984,
          "ram_percent": 33.0,
          "cpu_percent": 6.7,
          "process_rss_bytes": 3594326016
        },
        "gpus": [
          {
            "index": 0,
            "name": "NVIDIA GeForce RTX 4090",
            "driver": "595.71.05",
            "memory_total_mb": 24564,
            "memory_used_mb": 4407,
            "memory_free_mb": 19674,
            "util_percent": 0
          }
        ]
      },
      {
        "phase": "after_eval",
        "ts": "2026-07-07T01:21:03.938627Z",
        "sys": {
          "total_ram_bytes": 32702373888,
          "available_ram_bytes": 21762658304,
          "used_ram_bytes": 10939715584,
          "ram_percent": 33.5,
          "cpu_percent": 20.4,
          "process_rss_bytes": 3774697472
        },
        "gpus": [
          {
            "index": 0,
            "name": "NVIDIA GeForce RTX 4090",
            "driver": "595.71.05",
            "memory_total_mb": 24564,
            "memory_used_mb": 4407,
            "memory_free_mb": 19674,
            "util_percent": 13
          }
        ]
      }
    ],
    "profile": {
      "top_ops": [],
      "profiler_traces": [],
      "peak_cpu_rss_bytes": 3774697472,
      "peak_gpu_mb": 4407.0
    }
  }
}