[
    {
        "accuracy": 0.9472497745716862,
        "batch": 256,
        "dropout": 0.12934534069160958,
        "duration": 147959980612,
        "lr": 0.04122338470958785,
        "momentum": 0.20449801393643963,
        "transform": "norm",
        "uid": "ff7c2f0b90a9907dc2ba132fea9ecf26"
    },
    {
        "accuracy": 0.613515679791604,
        "batch": 256,
        "dropout": 0.2544643444162812,
        "duration": 186742785370,
        "lr": 0.00034973578670352643,
        "momentum": 0.7887206413393116,
        "transform": "echo_64",
        "uid": "712299c5a847fd7c0d9849a6cd788ff8"
    },
    {
        "accuracy": 0.613515679791604,
        "batch": 256,
        "dropout": 0.4655660721980284,
        "duration": 182163741275,
        "lr": 0.0038838649629655245,
        "momentum": 0.17810104766333779,
        "transform": "bf-v1-RandomSolarize_Pad",
        "uid": "f0b6892762c55b9500498b986506b58d"
    },
    {
        "accuracy": 0.613515679791604,
        "batch": 2048,
        "dropout": 0.03432153510496627,
        "duration": 249821144318,
        "lr": 0.20943062618124042,
        "momentum": 0.7047275554037368,
        "transform": "echo_128",
        "uid": "544bbcf3ad980000bdd7bc72492a5137"
    },
    {
        "accuracy": 0.6133152990682297,
        "batch": 128,
        "dropout": 0.49117715261069855,
        "duration": 181565457664,
        "lr": 1.561678855465982e-05,
        "momentum": 0.40706576919552007,
        "transform": "bf-v1-RandomCrop_RandomRotation",
        "uid": "3a946cfec612caaf624891b8d1bd02ba"
    }
]