{
  "model_name": "ga-684",
  "device_type": "Micro-Star International Co., Ltd. MS-7E27",
  "os_version": "Linux-6.8.0-111-generic-x86_64-with-glibc2.35",
  "valid": true,
  "emulator": false,
  "iterations": 20,
  "error_message": null,
  "unit": "NVIDIA GeForce RTX 4090",
  "duration": 6595606,
  "cpu_duration": 6595606,
  "cpu_min_duration": 6459758,
  "cpu_max_duration": 7482761,
  "cpu_std_dev": 227939.90814006928,
  "gpu_duration": 397054,
  "gpu_min_duration": 382111,
  "gpu_max_duration": 565248,
  "gpu_std_dev": 39922.279040933645,
  "total_ram_kb": 31935912,
  "free_ram_kb": 3460924,
  "available_ram_kb": 15136688,
  "cached_kb": 11582736,
  "in_dim_0": 1,
  "in_dim_1": 256,
  "in_dim_2": 256,
  "in_dim_3": 3,
  "device_analytics": {
    "timestamp": "2026-06-26T17:20:56.527002Z",
    "cpu_info": {
      "cpu_cores": 16,
      "processors": [
        {
          "vendor_id": "x86_64",
          "model": "x86_64"
        }
      ],
      "arm_architecture": null
    },
    "timeline": [
      {
        "phase": "before_eval",
        "ts": "2026-06-26T17:20:56.070983Z",
        "sys": {
          "total_ram_bytes": 32702373888,
          "available_ram_bytes": 15524741120,
          "used_ram_bytes": 17177632768,
          "ram_percent": 52.5,
          "cpu_percent": 6.6,
          "process_rss_bytes": 12588072960
        },
        "gpus": [
          {
            "index": 0,
            "name": "NVIDIA GeForce RTX 4090",
            "driver": "595.71.05",
            "memory_total_mb": 24564,
            "memory_used_mb": 6232,
            "memory_free_mb": 17849,
            "util_percent": 0
          }
        ]
      },
      {
        "phase": "after_eval",
        "ts": "2026-06-26T17:20:56.509371Z",
        "sys": {
          "total_ram_bytes": 32702373888,
          "available_ram_bytes": 15499968512,
          "used_ram_bytes": 17202405376,
          "ram_percent": 52.6,
          "cpu_percent": 26.5,
          "process_rss_bytes": 12673011712
        },
        "gpus": [
          {
            "index": 0,
            "name": "NVIDIA GeForce RTX 4090",
            "driver": "595.71.05",
            "memory_total_mb": 24564,
            "memory_used_mb": 6232,
            "memory_free_mb": 17849,
            "util_percent": 0
          }
        ]
      }
    ],
    "profile": {
      "top_ops": [],
      "profiler_traces": [],
      "peak_cpu_rss_bytes": 12673011712,
      "peak_gpu_mb": 6232.0
    }
  }
}