[
    {
        "accuracy": 0.8268,
        "batch": 8,
        "duration": 800116747153,
        "lr": 0.005423111163547985,
        "lr_now": 0.005423111163547985,
        "momentum": 0.8385446700919067,
        "transform": "bf-v1-RandomHorizontalFlip_RandomAutocontrast",
        "uid": "469d81b66b8950c18f514141fff896fa",
        "train_stat": {
            "train_loss": 0.12544771913078032,
            "test_loss": 0.5870759940332733,
            "train_accuracy": 0.9576,
            "gradient_norm": 1.4761031650222385,
            "samples_per_second": 1002.9499904067853,
            "best_accuracy": 0.8352,
            "best_epoch": 15,
            "cpu_count": 24,
            "cpu_type": "x86_64",
            "cpu_usage_percent": 12.2,
            "total_ram_kb": 32620620.0,
            "occupied_ram_kb": 15570408.0,
            "ram_usage_percent": 47.7,
            "gpu_type": "NVIDIA GeForce RTX 4090",
            "gpu_memory_kb": 5448892.0,
            "gpu_total_memory_kb": 24696896.0,
            "occupied_gpu_memory_kb": 26397.0,
            "gpu_memory_usage_percent": 0.11
        },
        "epoch_max": 50
    }
]
