[
    {
        "accuracy": 0.2897,
        "batch": 16,
        "best_accuracy": 0.2897,
        "best_epoch": 3,
        "dropout": 0.3988568101297775,
        "duration": 112628757179,
        "epoch_max": 5,
        "gpu_memory_kb": 1749808.5,
        "gradient_norm": 2.999999762496577,
        "lr": 0.10819455388598383,
        "lr_now": 0.10819455388598383,
        "momentum": 0.21754744807086257,
        "samples_per_second": 1331.2269908362314,
        "test_loss": 2.84373207950592,
        "train_accuracy": 0.31902,
        "train_loss": 2.646571425285339,
        "transform": "bf-v1-RandomAdjustSharpnes",
        "uid": "24010be3a998582b3be8e86a0a6bf94f"
    },
    {
        "accuracy": 0.2151,
        "batch": 32,
        "best_accuracy": 0.2151,
        "best_epoch": 3,
        "dropout": 0.08994816565917219,
        "duration": 122006000294,
        "epoch_max": 5,
        "gpu_memory_kb": 2772672.5,
        "gradient_norm": 2.9999995093635237,
        "lr": 0.0996921976302422,
        "lr_now": 0.0996921976302422,
        "momentum": 0.11301851690948272,
        "samples_per_second": 1230.9714766103114,
        "test_loss": 3.1507173407192046,
        "train_accuracy": 0.22338,
        "train_loss": 3.0967525689935957,
        "transform": "bf-v1-RandomHorizontalFlip_RandomCrop_Pad",
        "uid": "b54402d2963e2216998a2c306fe45117"
    }
]