[
    {
        "accuracy": 0.2856,
        "batch": 32,
        "duration": 280610593794,
        "lr": 0.08374554293958779,
        "metric_acc": 0.2856,
        "momentum": 0.3142198050362984,
        "transform": "echo_64",
        "uid": "1a535ff5c3ea0f372ad528fe3c25051c",
        "train_stat": {
            "train_loss": 1.877874573681954,
            "test_loss": 1.865233703543203,
            "train_accuracy": 0.28,
            "gradient_norm": 0.7439736425773236,
            "samples_per_second": 3762.8928679417895,
            "best_accuracy": 0.3013,
            "best_epoch": 20,
            "cpu_count": 24,
            "cpu_type": "x86_64",
            "cpu_usage_percent": 1.7,
            "total_ram_kb": 32627556.0,
            "occupied_ram_kb": 10527144.0,
            "ram_usage_percent": 32.3,
            "gpu_type": "NVIDIA GeForce RTX 4090",
            "gpu_memory_kb": 8603251.0,
            "gpu_total_memory_kb": 24658816.0,
            "occupied_gpu_memory_kb": 17677.5,
            "gpu_memory_usage_percent": 0.07
        },
        "epoch_max": 50
    }
]
