{
  "model_name": "alt-nn4-1fab59b3f2105b7f0ec136eeab2ce8a9",
  "device_type": "Micro-Star International Co., Ltd. MS-7E27",
  "os_version": "Linux-6.8.0-111-generic-x86_64-with-glibc2.35",
  "valid": true,
  "emulator": false,
  "iterations": 20,
  "error_message": null,
  "unit": "NVIDIA GeForce RTX 4090",
  "duration": 498737,
  "cpu_duration": 498737,
  "cpu_min_duration": 471281,
  "cpu_max_duration": 608753,
  "cpu_std_dev": 37600.667398820275,
  "gpu_duration": 230033,
  "gpu_min_duration": 220063,
  "gpu_max_duration": 262015,
  "gpu_std_dev": 9447.20134108064,
  "total_ram_kb": 31935912,
  "free_ram_kb": 3480620,
  "available_ram_kb": 15048856,
  "cached_kb": 11492124,
  "in_dim_0": 1,
  "in_dim_1": 64,
  "in_dim_2": 64,
  "in_dim_3": 3,
  "device_analytics": {
    "timestamp": "2026-06-26T16:17:25.695179Z",
    "cpu_info": {
      "cpu_cores": 16,
      "processors": [
        {
          "vendor_id": "x86_64",
          "model": "x86_64"
        }
      ],
      "arm_architecture": null
    },
    "timeline": [
      {
        "phase": "before_eval",
        "ts": "2026-06-26T16:17:25.630574Z",
        "sys": {
          "total_ram_bytes": 32702373888,
          "available_ram_bytes": 15426183168,
          "used_ram_bytes": 17276190720,
          "ram_percent": 52.8,
          "cpu_percent": 6.6,
          "process_rss_bytes": 12584902656
        },
        "gpus": [
          {
            "index": 0,
            "name": "NVIDIA GeForce RTX 4090",
            "driver": "595.71.05",
            "memory_total_mb": 24564,
            "memory_used_mb": 6232,
            "memory_free_mb": 17849,
            "util_percent": 0
          }
        ]
      },
      {
        "phase": "after_eval",
        "ts": "2026-06-26T16:17:25.678628Z",
        "sys": {
          "total_ram_bytes": 32702373888,
          "available_ram_bytes": 15409926144,
          "used_ram_bytes": 17292447744,
          "ram_percent": 52.9,
          "cpu_percent": 28.6,
          "process_rss_bytes": 12584906752
        },
        "gpus": [
          {
            "index": 0,
            "name": "NVIDIA GeForce RTX 4090",
            "driver": "595.71.05",
            "memory_total_mb": 24564,
            "memory_used_mb": 6232,
            "memory_free_mb": 17849,
            "util_percent": 0
          }
        ]
      }
    ],
    "profile": {
      "top_ops": [],
      "profiler_traces": [],
      "peak_cpu_rss_bytes": 12584906752,
      "peak_gpu_mb": 6232.0
    }
  }
}