[
    {
        "accuracy": 0.6865780577750461,
        "batch": 32,
        "best_accuracy": 0.7122387830362631,
        "best_epoch": 4,
        "dropout": 0.248928768942493,
        "duration": 632659016337,
        "epoch_max": 5,
        "gpu_memory_kb": 23188205.0,
        "gradient_norm": 2.999999512863072,
        "lr": 0.027692187553095698,
        "lr_now": 0.027692187553095698,
        "momentum": 0.667117013094306,
        "samples_per_second": 681.0072216847896,
        "test_loss": 1.2676109706008172,
        "train_accuracy": 0.7513821204799541,
        "train_loss": 0.9246181096117049,
        "transform": "bf-v1-RandomCrop_CenterCrop_RandomAutocontrast",
        "uid": "d943ba8add46b56557fb6388e2a23acb"
    },
    {
        "accuracy": 0.6358328211432084,
        "batch": 2,
        "best_accuracy": 0.6373693915181315,
        "best_epoch": 4,
        "dropout": 0.18275416217541324,
        "duration": 1579804056713,
        "epoch_max": 5,
        "gpu_memory_kb": 23188205.0,
        "gradient_norm": 1.193486703543982,
        "lr": 0.07249676973658116,
        "lr_now": 0.07249676973658116,
        "momentum": 0.02798034292241225,
        "samples_per_second": 229.09517297776642,
        "test_loss": 1.733595401726908,
        "train_accuracy": 0.7051066792251935,
        "train_loss": 1.2571230009671202,
        "transform": "bf-v1-RandomHorizontalFlip_Pad_CenterCrop",
        "uid": "1db4b54c936b23dc83320fe8d9e6d2cb"
    },
    {
        "accuracy": 0.25603103872157346,
        "batch": 16,
        "best_accuracy": 0.25603103872157346,
        "best_epoch": 5,
        "dropout": 0.4169078340480177,
        "duration": 736997361601,
        "epoch_max": 5,
        "gpu_memory_kb": 23188205.0,
        "gradient_norm": 2.9999999083263305,
        "lr": 0.00033503424972758703,
        "lr_now": 0.00033503424972758703,
        "momentum": 0.44807125325752706,
        "samples_per_second": 473.82321747893224,
        "test_loss": 2.1901513580610654,
        "train_accuracy": 0.28192527676536033,
        "train_loss": 2.124161077029946,
        "transform": "bf-v1-RandomCrop_RandomPosterize_RandomGrayscale",
        "uid": "362c6b976784d1f27b07db7af84bbbd6"
    },
    {
        "accuracy": 0.24508297480024585,
        "batch": 16,
        "best_accuracy": 0.24508297480024585,
        "best_epoch": 5,
        "dropout": 0.16651217266414664,
        "duration": 835029393842,
        "epoch_max": 5,
        "gpu_memory_kb": 23188205.0,
        "gradient_norm": 2.999999618982129,
        "lr": 7.627144208752363e-05,
        "lr_now": 7.627144208752363e-05,
        "momentum": 0.739320139117702,
        "samples_per_second": 395.8879373753643,
        "test_loss": 2.2048635767805993,
        "train_accuracy": 0.2578866183436395,
        "train_loss": 2.158946095712582,
        "transform": "bf-v1-RandomResizedCrop_65",
        "uid": "03644afd8b202b7d610594cbc0f365fd"
    },
    {
        "accuracy": 0.2175783650891211,
        "batch": 64,
        "best_accuracy": 0.219960049170252,
        "best_epoch": 4,
        "dropout": 0.2675496544056921,
        "duration": 678913145758,
        "epoch_max": 5,
        "gpu_memory_kb": 23188205.0,
        "gradient_norm": 2.9999997846062416,
        "lr": 1.965815322601755e-05,
        "lr_now": 1.965815322601755e-05,
        "momentum": 0.7350017616630128,
        "samples_per_second": 539.2815415318064,
        "test_loss": 2.239334773665857,
        "train_accuracy": 0.21920089547756527,
        "train_loss": 2.2355869049588666,
        "transform": "bf-v1-CenterCrop_RandomAdjustSharpnes_RandomPosterize",
        "uid": "53904f02338a9c1118e5692c2a5992b2"
    }
]