[
    {
        "accuracy": 0.518,
        "batch": 64,
        "duration": 1019053733948,
        "lr": 0.00899015783496739,
        "metric_acc": 0.518,
        "momentum": 0.4900305031143668,
        "transform": "bf-v1-RandomHorizontalFlip_RandomAdjustSharpnes_Pad",
        "uid": "1c2dff8d173a5b4d59934bc512dbf1bd",
        "train_stat": {
            "train_loss": 1.362234521857308,
            "test_loss": 1.373083317355745,
            "train_accuracy": 0.52432,
            "gradient_norm": 1.0000000225601764,
            "samples_per_second": 1477.126668151861,
            "best_accuracy": 0.518,
            "best_epoch": 30,
            "cpu_count": 24,
            "cpu_type": "x86_64",
            "cpu_usage_percent": 0.8,
            "total_ram_kb": 32627548.0,
            "occupied_ram_kb": 10809412.0,
            "ram_usage_percent": 33.1,
            "gpu_type": "NVIDIA GeForce RTX 4090",
            "gpu_memory_kb": 1362478.5,
            "gpu_total_memory_kb": 24658816.0,
            "occupied_gpu_memory_kb": 17911.5,
            "gpu_memory_usage_percent": 0.07
        },
        "epoch_max": 50
    },
    {
        "accuracy": 0.5016,
        "batch": 64,
        "duration": 399526032119,
        "lr": 0.00899015783496739,
        "momentum": 0.4900305031143668,
        "transform": "bf-v1-RandomHorizontalFlip_RandomAdjustSharpnes_Pad",
        "uid": "4eb4ad409fecba553068c117cf1798f0",
        "epoch_max": 50
    }
]
