{
  "model_name": "unq-4d6d4db3b6b0b986b9f5e62ba296a5b5",
  "device_type": "23106RN0DA",
  "os_version": "13 | TP1A.220624.014",
  "valid": true,
  "emulator": false,
  "iterations": 20,
  "duration": 2116,
  "unit": "CPU",
  "cpu_duration": 2116,
  "cpu_min_duration": 2061874000,
  "cpu_max_duration": 2170240000,
  "cpu_std_dev": 27138000.0,
  "gpu_duration": 4606,
  "gpu_min_duration": 4064626000,
  "gpu_max_duration": 5154253000,
  "gpu_std_dev": 299832000.0,
  "npu_duration": 4200,
  "npu_min_duration": 4030518000,
  "npu_max_duration": 5176929000,
  "npu_std_dev": 353776000.0,
  "total_ram_kb": 3809484,
  "free_ram_kb": 340164,
  "available_ram_kb": 1175932,
  "cached_kb": 966592,
  "in_dim_0": 1,
  "in_dim_1": 299,
  "in_dim_2": 299,
  "in_dim_3": 3,
  "device_analytics": {
    "timestamp": 1778888723.222073,
    "cpu_info": {
      "cpu_cores": 8,
      "processors": [
        {
          "processor": "0",
          "bogomips": "26.00",
          "features": "fp asimd evtstrm aes pmull sha1 sha2 crc32 atomics fphp asimdhp cpuid asimdrdm lrcpc dcpop asimddp",
          "cpu implementer": "0x41",
          "cpu architecture": "8",
          "cpu variant": "0x1",
          "cpu part": "0xd05",
          "cpu revision": "0"
        },
        {
          "processor": "1",
          "bogomips": "26.00",
          "features": "fp asimd evtstrm aes pmull sha1 sha2 crc32 atomics fphp asimdhp cpuid asimdrdm lrcpc dcpop asimddp",
          "cpu implementer": "0x41",
          "cpu architecture": "8",
          "cpu variant": "0x1",
          "cpu part": "0xd05",
          "cpu revision": "0"
        },
        {
          "processor": "2",
          "bogomips": "26.00",
          "features": "fp asimd evtstrm aes pmull sha1 sha2 crc32 atomics fphp asimdhp cpuid asimdrdm lrcpc dcpop asimddp",
          "cpu implementer": "0x41",
          "cpu architecture": "8",
          "cpu variant": "0x1",
          "cpu part": "0xd05",
          "cpu revision": "0"
        },
        {
          "processor": "3",
          "bogomips": "26.00",
          "features": "fp asimd evtstrm aes pmull sha1 sha2 crc32 atomics fphp asimdhp cpuid asimdrdm lrcpc dcpop asimddp",
          "cpu implementer": "0x41",
          "cpu architecture": "8",
          "cpu variant": "0x1",
          "cpu part": "0xd05",
          "cpu revision": "0"
        }
      ],
      "arm_architecture": {
        "hardware": "MT6768",
        "features": "fp asimd evtstrm aes pmull sha1 sha2 crc32 atomics fphp asimdhp cpuid asimdrdm lrcpc dcpop asimddp",
        "cpu_implementer": "0x41",
        "cpu_architecture": "8",
        "cpu_variant": "0x3",
        "cpu_part": "0xd0a",
        "cpu_revision": "1"
      }
    }
  }
}
