{
  "model_name": "unq-8eabf13766b9cf5f7ac12676dcbf1647",
  "device_type": "Pixel 4",
  "os_version": "13 | TP1A.221005.002.B2",
  "valid": true,
  "emulator": false,
  "iterations": 20,
  "duration": 273236,
  "unit": "CPU",
  "cpu_duration": 273236,
  "cpu_min_duration": 213000,
  "cpu_max_duration": 745000,
  "cpu_std_dev": 24000.0,
  "gpu_duration": 1321390,
  "gpu_min_duration": 232000,
  "gpu_max_duration": 7035000,
  "gpu_std_dev": 550000.0,
  "npu_duration": 2855770,
  "npu_min_duration": 1169000,
  "npu_max_duration": 9936000,
  "npu_std_dev": 918000.0,
  "total_ram_kb": 5596604,
  "free_ram_kb": 401116,
  "available_ram_kb": 2429208,
  "cached_kb": 2251060,
  "in_dim_0": 1,
  "in_dim_1": 30,
  "in_dim_2": 30,
  "in_dim_3": 3,
  "quantized_model_size_kib": 7.21,
  "device_analytics": {
    "timestamp": 1782077590.3544497,
    "cpu_info": {
      "cpu_cores": 8,
      "processors": [
        {
          "processor": "0",
          "bogomips": "38.00",
          "features": "fp asimd evtstrm aes pmull sha1 sha2 crc32 atomics fphp asimdhp cpuid asimdrdm lrcpc dcpop asimddp",
          "cpu implementer": "0x51",
          "cpu architecture": "8",
          "cpu variant": "0xd",
          "cpu part": "0x805",
          "cpu revision": "14"
        },
        {
          "processor": "1",
          "bogomips": "38.00",
          "features": "fp asimd evtstrm aes pmull sha1 sha2 crc32 atomics fphp asimdhp cpuid asimdrdm lrcpc dcpop asimddp",
          "cpu implementer": "0x51",
          "cpu architecture": "8",
          "cpu variant": "0xd",
          "cpu part": "0x805",
          "cpu revision": "14"
        },
        {
          "processor": "2",
          "bogomips": "38.00",
          "features": "fp asimd evtstrm aes pmull sha1 sha2 crc32 atomics fphp asimdhp cpuid asimdrdm lrcpc dcpop asimddp",
          "cpu implementer": "0x51",
          "cpu architecture": "8",
          "cpu variant": "0xd",
          "cpu part": "0x805",
          "cpu revision": "14"
        },
        {
          "processor": "3",
          "bogomips": "38.00",
          "features": "fp asimd evtstrm aes pmull sha1 sha2 crc32 atomics fphp asimdhp cpuid asimdrdm lrcpc dcpop asimddp",
          "cpu implementer": "0x51",
          "cpu architecture": "8",
          "cpu variant": "0xd",
          "cpu part": "0x805",
          "cpu revision": "14"
        }
      ],
      "arm_architecture": {
        "hardware": "Qualcomm Technologies, Inc SM8150",
        "features": "fp asimd evtstrm aes pmull sha1 sha2 crc32 atomics fphp asimdhp cpuid asimdrdm lrcpc dcpop asimddp",
        "cpu_implementer": "0x51",
        "cpu_architecture": "8",
        "cpu_variant": "0xd",
        "cpu_part": "0x804",
        "cpu_revision": "14"
      }
    }
  }
}