[
    {
        "accuracy": 0.6989279631299469,
        "batch": 128,
        "best_accuracy": 0.6989279631299469,
        "best_epoch": 1,
        "duration": 370105517459,
        "epoch_max": 1,
        "gpu_memory_kb": 233529.0,
        "gradient_norm": 0.8155516228752858,
        "lr": 0.005264034685284427,
        "lr_now": 0.005264034685284427,
        "momentum": 0.45537678053316233,
        "samples_per_second": 439.7937970297615,
        "test_loss": 0.5846930054517893,
        "train_accuracy": 0.6878478835166185,
        "train_loss": 0.5881287796692278,
        "transform": "bf-v1-RandomHorizontalFlip_Pad_RandomPosterize",
        "uid": "18c75f044571d74b3554c4912dfa2f15"
    }
]