[
    {
        "accuracy": 0.33121019108280253,
        "batch": 64,
        "dropout": 0.2960853195828389,
        "duration": 433701908650,
        "lr": 0.04461181218373115,
        "momentum": 0.6546579059975145,
        "transform": "bf-v1-Pad_RandomAdjustSharpnes_5",
        "uid": "b6bd4eb338d045a1d21d347ecc73ac3e",
        "train_stat": {
            "train_loss": 1.9264603974045933,
            "test_loss": 1.9808507273274083,
            "train_accuracy": 0.33329813074242265,
            "gradient_norm": 2.999999562603296,
            "samples_per_second": 43.104944890462995,
            "best_accuracy": 0.33121019108280253,
            "best_epoch": 2,
            "cpu_count": 128,
            "cpu_type": "x86_64",
            "cpu_usage_percent": 2.3,
            "total_ram_kb": 263737032.0,
            "occupied_ram_kb": 38927008.0,
            "ram_usage_percent": 15.7,
            "gpu_type": "NVIDIA GeForce RTX 3090",
            "gpu_memory_kb": 613454.5,
            "gpu_total_memory_kb": 24734080.0,
            "occupied_gpu_memory_kb": 45401.0,
            "gpu_memory_usage_percent": 0.18
        },
        "epoch_max": 5
    },
    {
        "accuracy": 0.19439490445859872,
        "batch": 32,
        "dropout": 0.04338209413176791,
        "duration": 182099321628,
        "lr": 0.3077036086578358,
        "momentum": 0.7960456473883877,
        "transform": "bf-v1-CenterCrop_RandomAdjustSharpnes_RandomPosterize",
        "uid": "01917a5a3be83d63df09e308006e3762",
        "train_stat": {
            "train_loss": 2.1854318936128876,
            "test_loss": 2.2069918566603,
            "train_accuracy": 0.21617911078255359,
            "gradient_norm": 0.454656238887108,
            "samples_per_second": 104.28642232997936,
            "best_accuracy": 0.19439490445859872,
            "best_epoch": 2,
            "cpu_count": 32,
            "cpu_type": "x86_64",
            "cpu_usage_percent": 0.0,
            "total_ram_kb": 131727448.0,
            "occupied_ram_kb": 4303488.0,
            "ram_usage_percent": 6.1,
            "gpu_type": "NVIDIA GeForce RTX 4090",
            "gpu_memory_kb": 24012950.0,
            "gpu_total_memory_kb": 24658816.0,
            "occupied_gpu_memory_kb": 45501.0,
            "gpu_memory_usage_percent": 0.18
        },
        "epoch_max": 5
    },
    {
        "accuracy": 0.19388535031847134,
        "batch": 4,
        "dropout": 0.010992910277486168,
        "duration": 437203737941,
        "lr": 0.16566946139885388,
        "lr_now": 0.16566946139885388,
        "momentum": 0.5138031658457825,
        "transform": "bf-v1-Pad_RandomPosterize_RandomAdjustSharpnes",
        "uid": "7fe4e04b8b9824c12c091effc3475634",
        "train_stat": {
            "train_loss": 2.1587192383217246,
            "test_loss": 2.1720727597858356,
            "train_accuracy": 0.19632484950892384,
            "gradient_norm": 2.9999996937209192,
            "samples_per_second": 43.39859670471734,
            "best_accuracy": 0.19388535031847134,
            "best_epoch": 2,
            "gpu_memory_kb": 76768.5
        },
        "epoch_max": 5
    },
    {
        "accuracy": 0.17885350318471338,
        "batch": 32,
        "dropout": 0.4195100881851091,
        "duration": 267394492411,
        "lr": 0.0009320438525923968,
        "momentum": 0.7193174673228541,
        "transform": "echo_299",
        "uid": "5ac1b40dab21a23b6dcbb86cc173f73b",
        "train_stat": {
            "train_loss": 2.2148963430443325,
            "test_loss": 2.2244193534540937,
            "train_accuracy": 0.19273418523603336,
            "gradient_norm": 2.9999998701220174,
            "samples_per_second": 70.5895005501255,
            "best_accuracy": 0.17885350318471338,
            "best_epoch": 2,
            "cpu_count": 128,
            "cpu_type": "x86_64",
            "cpu_usage_percent": 2.3,
            "total_ram_kb": 263737032.0,
            "occupied_ram_kb": 38694172.0,
            "ram_usage_percent": 15.6,
            "gpu_type": "NVIDIA GeForce RTX 3090",
            "gpu_memory_kb": 6020483.5,
            "gpu_total_memory_kb": 24734080.0,
            "occupied_gpu_memory_kb": 46106.5,
            "gpu_memory_usage_percent": 0.19
        },
        "epoch_max": 5
    },
    {
        "accuracy": 0.15082802547770702,
        "batch": 16,
        "dropout": 0.3238962291830945,
        "duration": 401487637894,
        "lr": 0.016381627452371133,
        "lr_now": 0.016381627452371133,
        "momentum": 0.17284702236599203,
        "transform": "bf-v1-RandomAdjustSharpnes_RandomRotation_3",
        "uid": "2e4632e175ce4af013ab60bf22717f42",
        "train_stat": {
            "train_loss": 2.252272413389103,
            "test_loss": 2.2599592611072508,
            "train_accuracy": 0.1635864399619812,
            "gradient_norm": 3.0000001909493226,
            "samples_per_second": 47.468155780569724,
            "best_accuracy": 0.15082802547770702,
            "best_epoch": 2,
            "gpu_memory_kb": 183333.0
        },
        "epoch_max": 5
    },
    {
        "accuracy": 0.14802547770700636,
        "batch": 64,
        "dropout": 0.11753607238083602,
        "duration": 379843130081,
        "lr": 0.01876882756260982,
        "momentum": 0.010952595716059887,
        "transform": "bf-v1-RandomEqualize_RandomAdjustSharpnes_2",
        "uid": "21ed17512778bc94596188cc1f16adfe",
        "train_stat": {
            "train_loss": 2.2703904090700924,
            "test_loss": 2.2728977780188284,
            "train_accuracy": 0.15070229168866828,
            "gradient_norm": 2.9999997512119325,
            "samples_per_second": 50.073743661517895,
            "best_accuracy": 0.14802547770700636,
            "best_epoch": 2,
            "cpu_count": 32,
            "cpu_type": "x86_64",
            "cpu_usage_percent": 0.3,
            "total_ram_kb": 131727448.0,
            "occupied_ram_kb": 4317324.0,
            "ram_usage_percent": 6.1,
            "gpu_type": "NVIDIA GeForce RTX 4090",
            "gpu_memory_kb": 24012950.0,
            "gpu_total_memory_kb": 24658816.0,
            "occupied_gpu_memory_kb": 45593.0,
            "gpu_memory_usage_percent": 0.18
        },
        "epoch_max": 5
    }
]
