[
    {
        "accuracy": 0.9626289950906722,
        "batch": 128,
        "dropout": 0.16847727810926172,
        "duration": 795145398072,
        "lr": 0.04546527849997019,
        "momentum": 0.39862990324516423,
        "transform": "bf-v1-RandomRotation_46",
        "uid": "0c79c85eab4f22854791a30ff9e3c47a"
    },
    {
        "accuracy": 0.9554152890491935,
        "batch": 128,
        "dropout": 0.36976005542698237,
        "duration": 1414870416668,
        "lr": 0.31705775012015314,
        "momentum": 0.07811778485308418,
        "transform": "bf-v1-Pad_RandomAdjustSharpnes_RandomHorizontalFlip",
        "uid": "5d350f9bf8b084c347d3444c9f5a1f76"
    },
    {
        "accuracy": 0.952459673379421,
        "batch": 1024,
        "dropout": 0.2464841443874516,
        "duration": 1083021662848,
        "lr": 0.07508448752819794,
        "momentum": 0.5154868048927373,
        "transform": "bf-v1-RandomPerspective_RandomPosterize_4",
        "uid": "9b35bea4f3925f2370d5a82d61a3c0f2"
    },
    {
        "accuracy": 0.613515679791604,
        "batch": 256,
        "dropout": 0.03080898794845205,
        "duration": 781717334526,
        "lr": 0.0003244125920112339,
        "momentum": 0.07130489452378064,
        "transform": "bf-v1-CenterCrop_Pad_RandomAdjustSharpnes",
        "uid": "e2878d9b080836f13ffb6ce13ba5033d"
    }
]