{
  "model_name": "MoE4Own-batch-00032-20260325-181059-79c3b29c227f5c3d44a8d8222a56f021",
  "device_type": "Micro-Star International Co., Ltd. MS-7E27",
  "os_version": "Linux-6.8.0-111-generic-x86_64-with-glibc2.35",
  "valid": true,
  "emulator": false,
  "iterations": 20,
  "error_message": null,
  "unit": "NVIDIA GeForce RTX 4090",
  "duration": 40799492,
  "cpu_duration": 40799492,
  "cpu_min_duration": 29959878,
  "cpu_max_duration": 98537512,
  "cpu_std_dev": 14827359.920921767,
  "gpu_duration": 3006059,
  "gpu_min_duration": 2890399,
  "gpu_max_duration": 3629983,
  "gpu_std_dev": 164452.00275758328,
  "total_ram_kb": 31935912,
  "free_ram_kb": 1079192,
  "available_ram_kb": 15413368,
  "cached_kb": 14183948,
  "in_dim_0": 1,
  "in_dim_1": 256,
  "in_dim_2": 256,
  "in_dim_3": 3,
  "device_analytics": {
    "timestamp": "2026-06-26T14:25:53.004783Z",
    "cpu_info": {
      "cpu_cores": 16,
      "processors": [
        {
          "vendor_id": "x86_64",
          "model": "x86_64"
        }
      ],
      "arm_architecture": null
    },
    "timeline": [
      {
        "phase": "before_eval",
        "ts": "2026-06-26T14:25:51.306812Z",
        "sys": {
          "total_ram_bytes": 32702373888,
          "available_ram_bytes": 15926030336,
          "used_ram_bytes": 16776343552,
          "ram_percent": 51.3,
          "cpu_percent": 6.7,
          "process_rss_bytes": 12069449728
        },
        "gpus": [
          {
            "index": 0,
            "name": "NVIDIA GeForce RTX 4090",
            "driver": "595.71.05",
            "memory_total_mb": 24564,
            "memory_used_mb": 1778,
            "memory_free_mb": 22303,
            "util_percent": 0
          }
        ]
      },
      {
        "phase": "after_eval",
        "ts": "2026-06-26T14:25:52.987259Z",
        "sys": {
          "total_ram_bytes": 32702373888,
          "available_ram_bytes": 15783747584,
          "used_ram_bytes": 16918626304,
          "ram_percent": 51.7,
          "cpu_percent": 38.2,
          "process_rss_bytes": 12287561728
        },
        "gpus": [
          {
            "index": 0,
            "name": "NVIDIA GeForce RTX 4090",
            "driver": "595.71.05",
            "memory_total_mb": 24564,
            "memory_used_mb": 1778,
            "memory_free_mb": 22303,
            "util_percent": 0
          }
        ]
      }
    ],
    "profile": {
      "top_ops": [],
      "profiler_traces": [],
      "peak_cpu_rss_bytes": 12287561728,
      "peak_gpu_mb": 1778.0
    }
  }
}