[
    {
        "accuracy": 0.9352,
        "batch": 2,
        "dropout": 0.22627464895771232,
        "duration": 128114542005,
        "epoch_max": 5,
        "lr": 0.016492825670311614,
        "momentum": 0.7434158133379153,
        "transform": "bf-v1-CenterCrop_Pad_RandomCrop",
        "uid": "cc3ce936cbddf0c02d14874c2eb62878"
    },
    {
        "accuracy": 0.9201,
        "batch": 32,
        "dropout": 0.45579375899244134,
        "duration": 12771126072,
        "lr": 0.001274317319861146,
        "momentum": 0.6977523079003113,
        "transform": "bf-v1-RandomGrayscale_Grayscale_2",
        "uid": "0356622e91db56df4bd802c4a64a02e7"
    },
    {
        "accuracy": 0.8638,
        "batch": 256,
        "dropout": 0.16085899235203405,
        "duration": 17426572957,
        "epoch_max": 5,
        "lr": 0.006944833914755221,
        "momentum": 0.15712663561813922,
        "transform": "bf-v1-RandomHorizontalFlip_RandomPosterize_RandomPerspective",
        "uid": "9a885b330313a3f661946298c072eb44"
    },
    {
        "accuracy": 0.727,
        "batch": 128,
        "dropout": 0.3254695134308374,
        "duration": 17698299455,
        "epoch_max": 5,
        "lr": 0.721045628042718,
        "momentum": 0.8209497342829443,
        "transform": "bf-v1-RandomHorizontalFlip_CenterCrop_Pad",
        "uid": "a4b25f6e5359e228608ec9208d66bef2"
    },
    {
        "accuracy": 0.3079,
        "batch": 256,
        "dropout": 0.252651830188172,
        "duration": 17421818399,
        "epoch_max": 5,
        "lr": 1.0860689548932372e-05,
        "momentum": 0.5874199806598417,
        "transform": "bf-v1-CenterCrop_RandomRotation_RandomHorizontalFlip",
        "uid": "854e49028638fc1f54ec618cdb71e231"
    },
    {
        "accuracy": 0.2974,
        "batch": 128,
        "dropout": 0.08831231924167376,
        "duration": 17365865137,
        "epoch_max": 5,
        "lr": 0.667200968487425,
        "momentum": 0.6506426659580359,
        "transform": "bf-v1-RandomRotation_46",
        "uid": "e2270edab2f9ba4d87043dc5bf9d80f2"
    }
]