[
    {
        "accuracy": 0.5563777836349796,
        "batch": 8,
        "best_accuracy": 0.5563991661458128,
        "best_epoch": 65,
        "cpu_count": 16,
        "cpu_type": "x86_64",
        "cpu_usage_percent": 0.0,
        "duration": 2010042406250,
        "epoch_max": 400,
        "gpu_memory_kb": 1353939.0,
        "gpu_memory_usage_percent": 0.72,
        "gpu_total_memory_kb": 24670016.0,
        "gpu_type": "NVIDIA GeForce RTX 4090",
        "gradient_norm": 1.7333254650466654,
        "metric_psnr": 0.5563777836349796,
        "occupied_gpu_memory_kb": 177572.5,
        "occupied_ram_kb": 12765344.0,
        "ram_usage_percent": 40.0,
        "samples_per_second": 28.09067227861574,
        "test_loss": 0.002157370362860652,
        "total_ram_kb": 31935504.0,
        "train_accuracy": 0.0,
        "train_loss": 0.11265978932380677,
        "transform": "complex_192",
        "uid": "14c7519d4bdc73c12dd566ecf2699b26"
    },
    {
        "accuracy": 0.549872429555918,
        "batch": 8,
        "best_accuracy": 0.549872429555918,
        "best_epoch": 70,
        "cpu_count": 16,
        "cpu_type": "x86_64",
        "cpu_usage_percent": 0.6,
        "duration": 2125182563423,
        "epoch_max": 400,
        "gpu_memory_kb": 2147137.5,
        "gpu_memory_usage_percent": 0.84,
        "gpu_total_memory_kb": 24670016.0,
        "gpu_type": "NVIDIA GeForce RTX 4090",
        "gradient_norm": 3.4267513094943833,
        "metric_psnr": 0.549872429555918,
        "occupied_gpu_memory_kb": 207194.5,
        "occupied_ram_kb": 13152076.0,
        "ram_usage_percent": 41.2,
        "samples_per_second": 26.263565164852654,
        "test_loss": 0.0023427670552896764,
        "total_ram_kb": 31935504.0,
        "train_accuracy": 0.0,
        "train_loss": 0.14438048489391803,
        "transform": "complex_192",
        "uid": "30cd62e7a7892b9ab924b2329921c4a7"
    }
]